{"name":"Partarch","tagline":"oracle database javafx fxml java webview jdbc","body":"PartArch\r\n========\r\nPartition Archiver(Partitioning Tool) for Oracle DB\r\n\r\nThe only option available now is \"EXCHANGE PARTITION\"\r\nBut the skeleton is ready, so its easy to add another functions.\r\n\r\n========\r\n\r\nUsing new ojdbc7.jar library is highly recomended because there is a few \"SELECT LONG\" columns and using ojdbc6.jar makes few queries executing very slow.\r\n\r\n========\r\n\r\n","google":"","note":"Don't delete this file! It's used internally to help with page regeneration."}